viewORCA/__init__.py
viewORCA/check_prerequisites.py
viewORCA/Programs/combine_systems_together.py
viewORCA/Programs/get_multiplicity.py
viewORCA/Programs/move_centre_of_mass.py
viewORCA/Programs/viewIRC.py
viewORCA/Programs/viewNEB.py
viewORCA/Programs/viewNEB_interpolate.py
viewORCA/Programs/viewNEB_snapshot.py
viewORCA/Programs/viewOPT.py
viewORCA/Programs/viewSCAN.py
viewORCA/Programs/viewIRC_methods/get_ORCA_IRC_images.py
viewORCA/Programs/viewIRC_methods/get_trajectory_filename.py
viewORCA/Programs/viewNEB_methods/get_MEP_trajectory_filename.py
viewORCA/Programs/viewNEB_methods/get_ORCA_NEB_images.py
viewORCA/Programs/viewNEB_snapshot_methods/get_interpolation_filename.py
viewORCA/Programs/viewNEB_snapshot_methods/plot_neb.py
viewORCA/Programs/viewNEB_snapshot_methods/read_orca_interpolation_file.py
viewORCA/Programs/viewOPT_methods/get_ORCA_OPT_images.py
viewORCA/Programs/viewOPT_methods/get_trajectory_filename.py
viewORCA/Programs/viewSCAN_methods/obtain_SCAN_information.py
viewORCA/Programs/viewSCAN_methods/obtain_SCAN_information_from_SCAN_folders.py
viewORCA/Programs/viewSCAN_methods/obtain_SCAN_information_method/assign_energies_to_SCAN_images.py
viewORCA/Programs/viewSCAN_methods/obtain_SCAN_information_method/get_ORCA_SCAN_images.py
viewORCA/Programs/viewSCAN_methods/utility_methods/does_contain_SCAN_files.py
viewORCA/Programs/viewSCAN_methods/utility_methods/does_contain_SCAN_folders.py
viewORCA/Programs/viewSCAN_methods/utility_methods/get_trajectory_filename.py
viewORCA/cli/main.py
viewORCA-0.2.2.data/scripts/viewORCA
viewORCA-0.2.2.dist-info/LICENSE
viewORCA-0.2.2.dist-info/METADATA
viewORCA-0.2.2.dist-info/WHEEL
viewORCA-0.2.2.dist-info/top_level.txt
viewORCA-0.2.2.dist-info/RECORD
