Metadata-Version: 2.1
Name: viewORCA
Version: 0.2.2
Summary: This program is designed to allow the user to inspect calculations from ORCA. This is to be used along side the ORCA Reaction Mechanism Tutorial.
Home-page: https://geoffreyweal.github.io/ORCA_Mechanism_Procedure/
Download-URL: https://github.com/geoffreyweal/viewORCA/archive/v0.2.2.tar.gz
Author: Dr. Geoffrey R. Weal
Author-email: geoffrey.weal@gmail.ac.nz
License: GNU AFFERO GENERAL PUBLIC LICENSE
Keywords: computational-chemistry,DFT,atomic-simulation-environment,ORCA
Classifier: Development Status :: 3 - Alpha
Classifier: Intended Audience :: Science/Research
Classifier: Natural Language :: English
Classifier: Operating System :: MacOS :: MacOS X
Classifier: Operating System :: POSIX :: Linux
Classifier: Operating System :: Unix
Classifier: Topic :: Scientific/Engineering :: Chemistry
Classifier: Topic :: Scientific/Engineering :: Physics
Classifier: Topic :: Scientific/Engineering :: Mathematics
Classifier: Natural Language :: English
Classifier: License :: OSI Approved :: GNU Affero General Public License v3
Classifier: Programming Language :: Python :: 3 :: Only
Classifier: Programming Language :: Python :: 3.6
Classifier: Programming Language :: Python :: 3.7
Classifier: Programming Language :: Python :: 3.8
Classifier: Programming Language :: Python :: 3.9
Classifier: Programming Language :: Python :: 3.10
Classifier: Programming Language :: Python :: 3.11
Classifier: Programming Language :: Python :: 3.12
License-File: LICENSE
Requires-Dist: packaging
Requires-Dist: numpy
Requires-Dist: scipy
Requires-Dist: matplotlib
Requires-Dist: ase >=3.19.0
